sdkrouter/__init__.py
sdkrouter/_client.py
sdkrouter/_config.py
sdkrouter/_constants.py
sdkrouter/_version.py
sdkrouter/logging.py
sdkrouter/_api/__init__.py
sdkrouter/_api/client.py
sdkrouter/_api/generated/__init__.py
sdkrouter/_api/generated/cdn/__init__.py
sdkrouter/_api/generated/cdn/client.py
sdkrouter/_api/generated/cdn/enums.py
sdkrouter/_api/generated/cdn/pyproject.toml
sdkrouter/_api/generated/cdn/sync_client.py
sdkrouter/_api/generated/cdn/cdn__api__cdn/__init__.py
sdkrouter/_api/generated/cdn/cdn__api__cdn/client.py
sdkrouter/_api/generated/cdn/cdn__api__cdn/models.py
sdkrouter/_api/generated/cdn/cdn__api__cdn/sync_client.py
sdkrouter/_api/generated/cdn/helpers/__init__.py
sdkrouter/_api/generated/cdn/helpers/logger.py
sdkrouter/_api/generated/cdn/helpers/retry.py
sdkrouter/_api/generated/cleaner/__init__.py
sdkrouter/_api/generated/cleaner/client.py
sdkrouter/_api/generated/cleaner/enums.py
sdkrouter/_api/generated/cleaner/pyproject.toml
sdkrouter/_api/generated/cleaner/sync_client.py
sdkrouter/_api/generated/cleaner/cleaner__api__cleaner/__init__.py
sdkrouter/_api/generated/cleaner/cleaner__api__cleaner/client.py
sdkrouter/_api/generated/cleaner/cleaner__api__cleaner/models.py
sdkrouter/_api/generated/cleaner/cleaner__api__cleaner/sync_client.py
sdkrouter/_api/generated/cleaner/helpers/__init__.py
sdkrouter/_api/generated/cleaner/helpers/logger.py
sdkrouter/_api/generated/cleaner/helpers/retry.py
sdkrouter/_api/generated/image_gen/__init__.py
sdkrouter/_api/generated/image_gen/client.py
sdkrouter/_api/generated/image_gen/enums.py
sdkrouter/_api/generated/image_gen/pyproject.toml
sdkrouter/_api/generated/image_gen/sync_client.py
sdkrouter/_api/generated/image_gen/helpers/__init__.py
sdkrouter/_api/generated/image_gen/helpers/logger.py
sdkrouter/_api/generated/image_gen/helpers/retry.py
sdkrouter/_api/generated/image_gen/image_gen__api__image_gen/__init__.py
sdkrouter/_api/generated/image_gen/image_gen__api__image_gen/client.py
sdkrouter-0.1.16.dist-info/METADATA
sdkrouter-0.1.16.dist-info/WHEEL
sdkrouter-0.1.16.dist-info/RECORD
