Metadata-Version: 2.4
Name: sdkrouter
Version: 0.1.16
Summary: Unified SDK for AI services with OpenAI compatibility
Project-URL: Homepage, https://github.com/markolofsen/sdkrouter
Project-URL: Documentation, https://sdkrouter.com
Project-URL: Repository, https://github.com/markolofsen/sdkrouter
Author-email: markolofsen <dev@markolofsen.com>
License-Expression: MIT
Keywords: ai,api,cdn,llm,ocr,openai,sdk,vision
Classifier: Development Status :: 4 - Beta
Classifier: Intended Audience :: Developers
Classifier: License :: OSI Approved :: MIT License
Classifier: Programming Language :: Python :: 3
Classifier: Programming Language :: Python :: 3.10
Classifier: Programming Language :: Python :: 3.11
Classifier: Programming Language :: Python :: 3.12
Classifier: Topic :: Software Development :: Libraries :: Python Modules
Requires-Python: >=3.10
Requires-Dist: httpx<1.0.0,>=0.28.0
Requires-Dist: openai<3.0.0,>=2.0.0
Requires-Dist: pydantic-settings>=2.7.0
Requires-Dist: pydantic<3.0.0,>=2.10.0
Requires-Dist: rich>=14.0.0
Requires-Dist: sdkrouter-tools>=0.1.0
Requires-Dist: tenacity>=9.1.0
Requires-Dist: tiktoken>=0.8.0
Provides-Extra: dev
Requires-Dist: build>=1.2.0; extra == 'dev'
Requires-Dist: ipykernel>=6.0.0; extra == 'dev'
Requires-Dist: jupyter>=1.0.0; extra == 'dev'
Requires-Dist: mypy>=1.15.0; extra == 'dev'
Requires-Dist: pytest-asyncio>=0.26.0; extra == 'dev'
Requires-Dist: pytest-cov>=6.0.0; extra == 'dev'
Requires-Dist: pytest>=8.3.0; extra == 'dev'
Requires-Dist: questionary>=2.1.0; extra == 'dev'
Requires-Dist: ruff>=0.9.0; extra == 'dev'
Requires-Dist: toml>=0.10.0; extra == 'dev'
Requires-Dist: twine>=6.0.0; extra == 'dev'
